[
  {
    "english": "He was talking hot on the live until the hollow tips made him go silent.",
    "japanese": "ライブ配信で威勢よく吠えてたが、特殊弾を喰らって黙り込みやがった。",
    "note": "talking hot: 挑発的な発言, hollow tips: 殺傷能力の高い弾丸"
  },
  {
    "english": "Stop capping about your lifestyle, we all know you're still living with your moms.",
    "japanese": "お前の生活について嘘つくのはやめろ。まだ親元にいるのはバレてんだよ。",
    "note": "capping: 嘘をつく, lifestyle: ギャング的な生き様"
  },
  {
    "english": "We caught that opp lacking and now he's just a memory on a t-shirt.",
    "japanese": "あの敵が隙を見せたから仕留めてやった。今じゃただの追悼Tシャツの思い出様だ。",
    "note": "lacking: 無防備な状態, memory on a t-shirt: 死んで追悼品になること"
  },
  {
    "english": "I'm finna spin the block until I find the rat who talked to the feds.",
    "japanese": "サツに密告したネズミを見つけるまで、あいつの街区を周回してやる。",
    "note": "spin the block: 敵地を巡回する, rat: 密告者, feds: 警察・当局"
  },
  {
    "english": "That blicky got a switch, it'll turn a tough guy into a ghost in seconds.",
    "japanese": "このチャカにはスイッチ（改造パーツ）が付いてる。タフな野郎も数秒で幽霊送りだ。",
    "note": "blicky: 銃, switch: フルオート改造パーツ"
  },
  {
    "english": "He's chasing clout so hard he's literally running towards his own funeral.",
    "japanese": "あいつは売名に必死すぎて、文字通り自分の葬式に向かって走ってるようなもんだ。",
    "note": "chasing clout: 売名行為"
  },
  {
    "english": "Smoking on that dead pack, the smell of failure is hitting different today.",
    "japanese": "くたばった奴のパックを吸ってるが、敗北者の臭いは格別だぜ。",
    "note": "smoking on [name] pack: 死んだ敵を侮辱するドリル特有の表現"
  },
  {
    "english": "Don't get lined up by a girl who belongs to the streets.",
    "japanese": "誰のものでもないような女にハメられて消されるんじゃねえぞ。",
    "note": "lined up: 罠にはめる, belongs to the streets: 不特定多数と関係を持つ女性への蔑称"
  },
  {
    "english": "He tried to run but gravity and lead kept him on the ground.",
    "japanese": "逃げようとしてたが、重力と鉛（弾丸）のせいで地面に這いつくばったままだったよ。",
    "note": "lead: 弾丸"
  },
  {
    "english": "Is it really a crime if the victim was a waste of oxygen anyway?",
    "japanese": "どのみち酸素の無駄遣いだった奴が被害者なら、それって本当に犯罪なのか？",
    "note": "waste of oxygen: 社会のゴミ（ブラックジョーク）"
  },
  {
    "english": "Free all my demons, they were just doing community service by cleaning up the field.",
    "japanese": "俺の仲間を解放しろ。あいつらは敵を掃除して地域奉仕してただけだ。",
    "note": "demons: 荒くれ者の仲間, cleaning up: 敵を排除すること"
  },
  {
    "english": "The funeral home is the only business thriving in this neighborhood.",
    "japanese": "この界隈で繁盛してるビジネスは葬儀屋だけだ。",
    "note": "thriving: 繁栄している（皮肉）"
  },
  {
    "english": "Keep that same energy when the red dot is sitting on your forehead.",
    "japanese": "赤い点（照準）がお前の額に乗ってる時も、その威勢を保ってろよ。",
    "note": "keep that same energy: 態度を変えるな"
  },
  {
    "english": "He went from a viral rapper to a digital cemetery in less than a week.",
    "japanese": "あいつは一週間足らずでバズったラッパーからデジタル墓場行きになった。",
    "note": "digital cemetery: ネット上の追悼ページ"
  },
  {
    "english": "Everything is dead, we ain't showing no mercy to anyone from that side.",
    "japanese": "全滅だ。あっち側の連中には慈悲なんて一切見せねえ。",
    "note": "Everything is dead: 敵対勢力への強い攻撃的スローガン"
  },
  {
    "english": "He thought he was a demon until he met the real devil in the dark.",
    "japanese": "自分が悪魔だと思い込んでやがったが、暗闇で本物の悪魔に会っちまったな。",
    "note": "demon: 恐れ知らずのワル"
  },
  {
    "english": "His mother's crying on the news while we're counting this dirty money.",
    "japanese": "あいつの母親がニュースで泣いてる間、俺たちは汚れた金を数えてるぜ。",
    "note": "dirty money: 不正な手段で稼いだ金"
  },
  {
    "english": "I'd rather be judged by twelve jurors than carried by six friends.",
    "japanese": "6人の友人に棺桶を担がれるより、12人の陪審員に裁かれる方がマシだ。",
    "note": "死ぬよりは刑務所へ行く方が良いという覚悟の表現"
  },
  {
    "english": "Stop acting like you're about that life when you've never seen a cell.",
    "japanese": "監獄すら見たことないくせに、極道ぶるんじゃねえよ。",
    "note": "about that life: その道（犯罪・ギャング）の人間であること"
  },
  {
    "english": "He's getting a dirt nap tonight for all that internet barking.",
    "japanese": "ネットであれだけ吠えてた報いだ。今夜は土の下で寝かせてやる。",
    "note": "dirt nap: 死ぬこと, barking: （犬のように）吠える・虚勢を張る"
  },
  {
    "english": "The only thing he ever hit was the floor when the metal rang out.",
    "japanese": "あいつが当てた唯一のものは、銃声が響いた時の床面だけだったな。",
    "note": "狙いが外れたことと、即座に倒れたことを揶揄する表現"
  },
  {
    "english": "If you keep moving sus, you might not make it to see the sunrise.",
    "japanese": "そんな怪しい動きを続けてたら、日の出を拝むことはできねえぞ。",
    "note": "sus: 怪しい・不審な, make it: 生き残る"
  },
  {
    "english": "That glizzy made him dance better than any viral trend.",
    "japanese": "あの鉄砲はお前をどんな流行りの動画よりも上手く躍らせてくれたぜ。",
    "note": "glizzy: 銃"
  },
  {
    "english": "The streets are a graveyard for kids who thought they were bulletproof.",
    "japanese": "ストリートは、自分が不死身だと思い込んだガキどもの墓場だ。",
    "note": "bulletproof: 防弾の・不死身の"
  },
  {
    "english": "He's a whole pack now, stop asking about his whereabouts.",
    "japanese": "あいつはもうただの死体だ。行方なんて聞くのはやめろ。",
    "note": "whole pack: 故人（蔑称）"
  },
  {
    "english": "I don't need a degree when I'm making more than your professor in the trap.",
    "japanese": "アジトで教授より稼いでるんだから、学位なんていらねえよ。",
    "note": "trap: 麻薬密売所・溜まり場"
  },
  {
    "english": "He's lucky the gun jammed, or he'd be a headline instead of a witness.",
    "japanese": "銃が詰まってラッキーだったな。じゃなきゃ目撃者じゃなくニュースの見出しになるところだったぜ。",
    "note": "jammed: 弾詰まりを起こした"
  },
  {
    "english": "We don't do no talking, we let the hollow points do the chatting for us.",
    "japanese": "俺たちは喋らねえ。弾丸に代わりに喋ってもらうのさ。",
    "note": "hollow points: 拡張弾頭（殺傷力の高い弾）"
  },
  {
    "english": "You're crashing out for a block that doesn't even know your name.",
    "japanese": "お前の名前すら知らないような地元の名誉のために、人生棒に振るのかよ。",
    "note": "crashing out: 無謀な行動で自滅すること"
  },
  {
    "english": "The last thing he saw was the muzzle flash before everything went dark.",
    "japanese": "視界が真っ暗になる前にあいつが見た最後のものは、銃口の閃光だった。",
    "note": "muzzle flash: 銃を撃った時の火花"
  }
]